outliers_101703161/__init__.py
outliers_101703161/outliers.py
outliers_101703161-0.0.1.dist-info/LICENSE.txt
outliers_101703161-0.0.1.dist-info/METADATA
outliers_101703161-0.0.1.dist-info/WHEEL
outliers_101703161-0.0.1.dist-info/top_level.txt
outliers_101703161-0.0.1.dist-info/RECORD
